sysopt/__init__.py
sysopt/exceptions.py
sysopt/helpers.py
sysopt/version.py
sysopt/warnings.py
sysopt/backends/__init__.py
sysopt/backends/backends.py
sysopt/backends/implementation_hooks.py
sysopt/backends/casadi/__init__.py
sysopt/backends/casadi/codesign_solver.py
sysopt/backends/casadi/expression_graph.py
sysopt/backends/casadi/foreign_function.py
sysopt/backends/casadi/integrator.py
sysopt/backends/casadi/math.py
sysopt/backends/casadi/path.py
sysopt/backends/casadi/variational_solver.py
sysopt/backends/sympy/__init__.py
sysopt/backends/sympy/expression_graph.py
sysopt/backends/sympy/helpers.py
sysopt/backends/sympy/integrator.py
sysopt/backends/sympy/math.py
sysopt/blocks/__init__.py
sysopt/blocks/common.py
sysopt/blocks/discrete_controllers.py
sysopt/blocks/optimal_controllers.py
sysopt/modelling/__init__.py
sysopt/modelling/block.py
sysopt/modelling/builders.py
sysopt/modelling/types.py
sysopt/problems/__init__.py
sysopt/problems/canonical_transform.py
sysopt/problems/problem_data.py
sysopt/problems/solver.py
sysopt/problems/wiring_tables.py
sysopt/symbolic/__init__.py
sysopt/symbolic/core.py
sysopt/symbolic/decision_variables.py
sysopt/symbolic/scalar_ops.py
sysopt-0.6.4.dist-info/LICENSE
sysopt-0.6.4.dist-info/METADATA
sysopt-0.6.4.dist-info/WHEEL
sysopt-0.6.4.dist-info/top_level.txt
sysopt-0.6.4.dist-info/RECORD
