Metadata-Version: 2.1
Name: sysopt
Version: 0.6.4
Summary: Component-based systems modelling library.
Home-page: https://github.com/csp-at-unimelb/sysopt
Author: Peter Cudmore
Author-email: peter.cudmore@uqconnect.edu.au
Classifier: Programming Language :: Python :: 3
Classifier: License :: OSI Approved :: Apache Software License
Classifier: Topic :: Scientific/Engineering
Classifier: Topic :: Software Development :: Libraries
License-File: LICENSE
Requires-Dist: numpy (>=1.20)
Requires-Dist: scipy
Requires-Dist: ordered-set
Requires-Dist: casadi ; platform_machine != "arm64"
